COPYING
MANIFEST.in
README.rst
buildout.cfg
requirements.txt
setup.py
version.txt
bob/__init__.py
bob.hobpad2.chapter19.egg-info/PKG-INFO
bob.hobpad2.chapter19.egg-info/SOURCES.txt
bob.hobpad2.chapter19.egg-info/dependency_links.txt
bob.hobpad2.chapter19.egg-info/entry_points.txt
bob.hobpad2.chapter19.egg-info/requires.txt
bob.hobpad2.chapter19.egg-info/top_level.txt
bob/hobpad2/__init__.py
bob/hobpad2/chapter19/__init__.py
bob/hobpad2/chapter19/plot_far_frr_pad.py
bob/hobpad2/chapter19/plot_pad_results.py