Metadata-Version: 1.1
Name: bob.hobpad2.chapter19
Version: 1.0.1
Summary: Software package to reproduce Evaluation Methodologies for Biometric Presentation Attack Detection chapter of Handbook of Biometric Anti-Spoofing: Presentation Attack Detection 2nd Edition
Home-page: https://gitlab.idiap.ch/bob/bob.hobpad2.chapter19
Author: Pavel Korshunov
Author-email: pavel.korshunov@idiap.ch
License: GPLv3
Keywords: bob
Platform: UNKNOWN
Classifier: Framework :: Bob
Classifier: Development Status :: 4 - Beta
Classifier: Intended Audience :: Developers
Classifier: License :: OSI Approved :: GNU General Public License v3 (GPLv3)
Classifier: Natural Language :: English
Classifier: Programming Language :: Python
Classifier: Programming Language :: Python :: 3
Classifier: Topic :: Scientific/Engineering :: Artificial Intelligence
Classifier: Topic :: Software Development :: Libraries :: Python Modules
